csplot/__init__.py
csplot-0.2.1.dist-info/LICENSE
csplot-0.2.1.dist-info/METADATA
csplot-0.2.1.dist-info/WHEEL
csplot-0.2.1.dist-info/top_level.txt
csplot-0.2.1.dist-info/RECORD
